{
  "recentFiles": [
    {
      "basename": "商业计划书",
      "path": "private/01-Diary/本周事务/商业计划书.md"
    },
    {
      "basename": "数值分析作业-拟合和最小二乘法",
      "path": "private/01-Diary/本周事务/数值分析作业-拟合和最小二乘法.md"
    },
    {
      "basename": "Zhensong.Chen",
      "path": "private/02-Reading/3-people/Zhensong.Chen.md"
    },
    {
      "basename": "Humberto Bustince",
      "path": "private/02-Reading/3-people/Humberto Bustince.md"
    },
    {
      "basename": "2022-04-02_文献阅读小结",
      "path": "private/02-Reading/summary/2022-04-02_文献阅读小结.md"
    },
    {
      "basename": "2022-05-24_文献阅读小结",
      "path": "private/02-Reading/summary/2022-05-24_文献阅读小结.md"
    },
    {
      "basename": "大牛页面模板",
      "path": "private/09-Templates/大牛页面模板.md"
    },
    {
      "basename": "Luis Martínez",
      "path": "private/02-Reading/3-people/Luis Martínez.md"
    },
    {
      "basename": "常用工具",
      "path": "private/08-Assets/Scripts/常用工具.md"
    },
    {
      "basename": "任务看板",
      "path": "private/00-MOC/任务看板.md"
    },
    {
      "basename": "本周事务表",
      "path": "private/00-MOC/本周事务表.md"
    },
    {
      "basename": "数值分析作业-数值微分",
      "path": "private/01-Diary/本周事务/数值分析作业-数值微分.md"
    },
    {
      "basename": "草稿模板",
      "path": "private/09-Templates/草稿模板.md"
    },
    {
      "basename": "概率论作业-第四章+第五章",
      "path": "private/01-Diary/本周事务/概率论作业-第四章+第五章.md"
    },
    {
      "basename": "2023-04-16",
      "path": "private/01-Diary/日志存档/2023-04-16.md"
    },
    {
      "basename": "TO-DO list",
      "path": "private/00-MOC/TO-DO list.md"
    },
    {
      "basename": "Drawing 2023-05-12 21.50.07.excalidraw",
      "path": "private/08-Assets/Excalidraw/Drawing 2023-05-12 21.50.07.excalidraw.md"
    },
    {
      "basename": "Drawing 2023-05-04 20.20.15.excalidraw",
      "path": "private/08-Assets/Excalidraw/Drawing 2023-05-04 20.20.15.excalidraw.md"
    },
    {
      "basename": "test",
      "path": "private/01-Diary/本周事务/test.md"
    },
    {
      "basename": "每月总结",
      "path": "private/09-Templates/每月总结.md"
    },
    {
      "basename": "每周文献小结",
      "path": "private/09-Templates/每周文献小结.md"
    },
    {
      "basename": "词条模板",
      "path": "private/09-Templates/词条模板.md"
    },
    {
      "basename": "代码整理模板",
      "path": "private/09-Templates/代码整理模板.md"
    },
    {
      "basename": "概括文章骨架",
      "path": "private/09-Templates/概括文章骨架.md"
    },
    {
      "basename": "卡片模板",
      "path": "private/09-Templates/卡片模板.md"
    },
    {
      "basename": "论文草稿模板",
      "path": "private/09-Templates/论文草稿模板.md"
    },
    {
      "basename": "论文大纲模板",
      "path": "private/09-Templates/论文大纲模板.md"
    },
    {
      "basename": "日志模板",
      "path": "private/09-Templates/日志模板.md"
    },
    {
      "basename": "FastStart-Plugins-LongDelay",
      "path": "private/03-Projects/97-作业-杂项/FastStart-Plugins-LongDelay.md"
    },
    {
      "basename": "FastStart-Plugins-ShortDelay",
      "path": "private/03-Projects/97-作业-杂项/FastStart-Plugins-ShortDelay.md"
    },
    {
      "basename": "概率论与数理统计-第四章作业",
      "path": "term/Homework/概率论与数理统计-第四章作业.md"
    },
    {
      "basename": "信息论第二次作业-1-2",
      "path": "term/Homework/信息论第二次作业-1-2.md"
    },
    {
      "basename": "数值分析作业-第五次作业 1",
      "path": "term/Homework/数值分析作业-第五次作业 1.md"
    },
    {
      "basename": "数值分析作业-第四次作业 1",
      "path": "term/Homework/数值分析作业-第四次作业 1.md"
    },
    {
      "basename": "数值分析作业-插值",
      "path": "term/Homework/数值分析作业-插值.md"
    },
    {
      "basename": "Zotero多设备同步解决方案",
      "path": "term/haha/Zotero多设备同步解决方案.md"
    },
    {
      "basename": "Chapter5-",
      "path": "private/01-Diary/本周事务/Chapter5-.md"
    },
    {
      "basename": "slider test",
      "path": "private/03-Projects/09-Slides/slider test.md"
    },
    {
      "basename": "能见度工创PPT",
      "path": "private/01-Diary/本周事务/能见度工创PPT.md"
    },
    {
      "basename": "Minal-slides",
      "path": "private/03-Projects/09-Slides/Minal-slides.md"
    },
    {
      "basename": "Gram-Schmidt",
      "path": "term/ref/Gram-Schmidt.md"
    },
    {
      "basename": "Halo-Master-Chief-Collection 通关后",
      "path": "private/01-Diary/本周事务/Halo-Master-Chief-Collection 通关后.md"
    },
    {
      "basename": "Buttons",
      "path": "private/08-Assets/Scripts/Buttons.md"
    },
    {
      "basename": "2023-05-06",
      "path": "private/01-Diary/日志存档/2023-05-06.md"
    },
    {
      "basename": "2022-04-02",
      "path": "private/01-Diary/日志存档/2022-04-02.md"
    },
    {
      "basename": "Chapter 3 -System of Equation",
      "path": "private/01-Diary/本周事务/Chapter 3 -System of Equation.md"
    },
    {
      "basename": "2023-04-17",
      "path": "private/01-Diary/日志存档/2023-04-17.md"
    },
    {
      "basename": "Chapter12-Eigenvalues and singular values",
      "path": "private/01-Diary/本周事务/Chapter12-Eigenvalues and singular values.md"
    },
    {
      "basename": "愿望清单",
      "path": "private/00-MOC/愿望清单.md"
    },
    {
      "basename": "试剂库存管理",
      "path": "private/00-MOC/试剂库存管理.md"
    }
  ],
  "omittedPaths": [],
  "maxLength": null
}